vedro_allure_reporter/__init__.py
vedro_allure_reporter/_allure_labels.py
vedro_allure_reporter/_allure_reporter.py
vedro_allure_reporter/_allure_steps.py
vedro_allure_reporter/py.typed
vedro_allure_reporter/allure_rerunner/__init__.py
vedro_allure_reporter/allure_rerunner/_allure_rerunner.py
vedro_allure_reporter/allure_rerunner/_allure_scheduler.py
vedro_allure_reporter-1.12.0.dist-info/licenses/LICENSE
vedro_allure_reporter-1.12.0.dist-info/METADATA
vedro_allure_reporter-1.12.0.dist-info/WHEEL
vedro_allure_reporter-1.12.0.dist-info/top_level.txt
vedro_allure_reporter-1.12.0.dist-info/RECORD
