Metadata-Version: 2.4
Name: vedro-allure-reporter
Version: 1.12.0
Summary: Allure reporter for Vedro testing framework
Home-page: https://github.com/vedro-universe/vedro-allure-reporter
Author: Nikita Tsvetkov
Author-email: tsv1@fastmail.com
License: Apache-2.0
Project-URL: Docs, https://vedro.io/docs/integrations/allure-reporter
Project-URL: GitHub, https://github.com/vedro-universe/vedro-allure-reporter
Classifier: License :: OSI Approved :: Apache Software License
Classifier: Programming Language :: Python :: 3.8
Classifier: Programming Language :: Python :: 3.9
Classifier: Programming Language :: Python :: 3.10
Classifier: Programming Language :: Python :: 3.11
Classifier: Programming Language :: Python :: 3.12
Classifier: Programming Language :: Python :: 3.13
Classifier: Typing :: Typed
Requires-Python: >=3.8
License-File: LICENSE
Requires-Dist: vedro<2.0,>=1.7
Requires-Dist: allure-python-commons<3.0,>=2.9
Dynamic: author
Dynamic: author-email
Dynamic: classifier
Dynamic: description
Dynamic: description-content-type
Dynamic: home-page
Dynamic: license
Dynamic: license-file
Dynamic: project-url
Dynamic: requires-dist
Dynamic: requires-python
Dynamic: summary
